[
  { "name" : "candidate_roi", "color" : "#18b497", "description" : "Candidate ROI" },
  { "name" : "chosen_roi", "color" : "#2816ba", "description" : "ROI Chosen for validation" },
  { "name" : "inprogress_roi", "color" : "#f97a8a", "description" : "ROI being counted currently" },
  { "name" : "finished_roi", "color" : "#0bc027", "description" : "ROI that has been completed" },
  { "name" : "approved_roi", "color" : "#77d4c8", "description" : "ROI that has been inspected by another rater" },
  { "name" : "tangle", "color" : "#ca06c9", "description" : "Tangle" },
  { "name" : "pretangle", "color" : "#b095b8", "description" : "Pretangle, not a tangle yet"},
  { "name" : "ask_dave", "color" : "#76916b", "description" : "Placeholder, replace with actual label later"},
  { "name" : "rated_roi_0_none", "color" : "#ffca80", "description" : "Severity 0"},
  { "name" : "rated_roi_01_rare", "color" : "#ffb54d", "description" : "Severity 0-1"},
  { "name" : "rated_roi_1_mild", "color" : "#ff9f1a", "description" : "Severity 1"},
  { "name" : "rated_roi_2_moderate", "color" : "#e68600", "description" : "Severity 2"},
  { "name" : "rated_roi_3_severe", "color" : "#b36800", "description" : "Severity 3"}
]
